smfishHmrf/DatasetMatrix.py
smfishHmrf/HMRFInstance.py
smfishHmrf/__init__.py
smfishHmrf/bias_correction.py
smfishHmrf/reader.py
smfishHmrf/spatial.py
smfishHmrf/visualize.py
smfishHmrf/graphColoring/Backtracking.java
smfishHmrf/graphColoring/Clique.class
smfishHmrf/graphColoring/Clique.java
smfishHmrf/graphColoring/Constants.class
smfishHmrf/graphColoring/Constants.java
smfishHmrf/graphColoring/Graph.class
smfishHmrf/graphColoring/Graph.java
smfishHmrf/graphColoring/GraphColoring$PossibleColorsComparator.class
smfishHmrf/graphColoring/GraphColoring.class
smfishHmrf/graphColoring/GraphColoring.java
smfishHmrf/graphColoring/GraphReader.class
smfishHmrf/graphColoring/GraphReader.java
smfishHmrf/graphColoring/IteratedGreedy$ColorClass.class
smfishHmrf/graphColoring/IteratedGreedy$DecreasingComparator.class
smfishHmrf/graphColoring/IteratedGreedy$IncreasingComparator.class
smfishHmrf/graphColoring/IteratedGreedy.class
smfishHmrf/graphColoring/IteratedGreedy.java
smfishHmrf/graphColoring/LocalSearch.class
smfishHmrf/graphColoring/LocalSearch.java
smfishHmrf/graphColoring/MaxClique.class
smfishHmrf/graphColoring/MaxClique.java
smfishHmrf/graphColoring/Node.class
smfishHmrf/graphColoring/Node.java
smfishHmrf/graphColoring/SortedListNode.class
smfishHmrf/graphColoring/SortedListNode.java
smfishHmrf-1.3.3.dist-info/LICENSE
smfishHmrf-1.3.3.dist-info/METADATA
smfishHmrf-1.3.3.dist-info/WHEEL
smfishHmrf-1.3.3.dist-info/top_level.txt
smfishHmrf-1.3.3.dist-info/RECORD
