Metadata-Version: 2.1
Name: smfishHmrf
Version: 1.3.3
Summary: HMRF for spatial transcriptomic data
Home-page: https://bitbucket.org/qzhu/smfish-hmrf
Author: Qian Zhu
Author-email: zqian@jimmy.harvard.edu
License: UNKNOWN
Platform: UNKNOWN
Classifier: Programming Language :: Python :: 3
Classifier: License :: OSI Approved :: MIT License
Classifier: Operating System :: OS Independent
Requires-Python: >=3.5
Requires-Dist: scipy
Requires-Dist: numpy
Requires-Dist: pandas
Requires-Dist: seaborn
Requires-Dist: matplotlib
